pyat2/__init__.py
pyat2/cli.py
pyat2/version.py
pyat2-1.0.2.dist-info/METADATA
pyat2-1.0.2.dist-info/WHEEL
pyat2-1.0.2.dist-info/entry_points.txt
pyat2-1.0.2.dist-info/top_level.txt
pyat2-1.0.2.dist-info/RECORD
