Metadata-Version: 2.1
Name: pyat2
Version: 1.0.2
Summary: python version of at command in ubuntu
Home-page: UNKNOWN
Author: UNKNOWN
Author-email: UNKNOWN
License: UNKNOWN
Platform: UNKNOWN
